jupyter2clipboard/__init__.py
jupyter2clipboard/jupyter2clipboard.py
jupyter2clipboard-0.2.1.dist-info/LICENSE
jupyter2clipboard-0.2.1.dist-info/METADATA
jupyter2clipboard-0.2.1.dist-info/WHEEL
jupyter2clipboard-0.2.1.dist-info/top_level.txt
jupyter2clipboard-0.2.1.dist-info/RECORD
